logging_bootstrap-1.0.0.dist-info/METADATA
logging_bootstrap-1.0.0.dist-info/RECORD
logging_bootstrap-1.0.0.dist-info/WHEEL
logging_bootstrap-1.0.0.dist-info/top_level.txt
loggingbootstrap/__init__.py
loggingbootstrap/settings.py
